stan_utility/__init__.py
stan_utility/__version__.py
stan_utility/file_utils.py
stan_utility/save_fit.py
stan_utility/stan_generator.py
stan_utility/stan_utility.py
stan_utility/utils.py
stan_utility-0.1.2.dist-info/LICENSE
stan_utility-0.1.2.dist-info/METADATA
stan_utility-0.1.2.dist-info/WHEEL
stan_utility-0.1.2.dist-info/top_level.txt
stan_utility-0.1.2.dist-info/RECORD
