Metadata-Version: 2.1
Name: stan-utility
Version: 0.1.2
Summary: Helper routines for pystan based off @betanalphas stan_utility
Home-page: https://github.com/grburgess/stan_utility
Author: J. Michael Burgess
Author-email: jmichaelburgess@gmail.com
License: BSD
Platform: UNKNOWN
Requires-Python: >=2.7.0
Requires-Dist: numpy
Requires-Dist: scipy
Requires-Dist: h5py
Requires-Dist: pystan
Requires-Dist: pandas
